globus_jupyterlab/__init__.py
globus_jupyterlab/_version.py
globus_jupyterlab/exc.py
globus_jupyterlab/globus_config.py
globus_jupyterlab/login_manager.py
globus_jupyterlab/models.py
globus_jupyterlab/handlers/__init__.py
globus_jupyterlab/handlers/auth.py
globus_jupyterlab/handlers/base.py
globus_jupyterlab/handlers/config.py
globus_jupyterlab/handlers/exception_handlers.py
globus_jupyterlab/handlers/login.py
globus_jupyterlab/handlers/api/__init__.py
globus_jupyterlab/handlers/api/sdk_wrappers.py
globus_jupyterlab/handlers/api/transfer.py
globus_jupyterlab/labextension/package.json
globus_jupyterlab/labextension/schemas/globus_jupyterlab/globus_jupyterlab.json
globus_jupyterlab/labextension/schemas/globus_jupyterlab/package.json.orig
globus_jupyterlab/labextension/schemas/globus_jupyterlab/plugin.json
globus_jupyterlab/labextension/static/03f2986c0824c68bdaf1e16947352f5fe417d03741806097fa9ea7131fe3a019.ttf
globus_jupyterlab/labextension/static/236.9ece105134b772709954.js
globus_jupyterlab/labextension/static/236.9ece105134b772709954.js.LICENSE.txt
globus_jupyterlab/labextension/static/36.a67945025611282e58cd.js
globus_jupyterlab/labextension/static/404c746c8f7e3f9b7611a8f23d908c1a32a5c972236b9d89bb68b05d9bf4b905.woff2
globus_jupyterlab/labextension/static/4e96a7e098e36fd493194c64e973ba5237da65760c7b746217e63c830326a9ac.ttf
globus_jupyterlab/labextension/static/549.ed8fb6f70922762f9aab.js
globus_jupyterlab/labextension/static/6a274e7629c0d71dcf8cab1e7733687ebfe32e2c53b4ca9fad050b4f1d5471f3.woff2
globus_jupyterlab/labextension/static/804.2b367af87e1b69a2e312.js
globus_jupyterlab/labextension/static/819.8fbe009aa31e8514e700.js
globus_jupyterlab/labextension/static/819.8fbe009aa31e8514e700.js.LICENSE.txt
globus_jupyterlab/labextension/static/86a687cf5ade691e19aa03720ffa7c1ba99dd137f36cc61980eec447f2160627.ttf
globus_jupyterlab/labextension/static/909.22a554c180b0958a73ac.js
globus_jupyterlab-1.0.0b10.dist-info/METADATA
globus_jupyterlab-1.0.0b10.dist-info/WHEEL
globus_jupyterlab-1.0.0b10.dist-info/top_level.txt
globus_jupyterlab-1.0.0b10.dist-info/RECORD
