Metadata-Version: 2.1
Name: globus-jupyterlab
Version: 1.0.0b10
Summary: JupyterLab extension that incorporates Globus functionality
Home-page: https://github.com/globus/globus-jupyterlab
Author: The Globus Team
License: BSD-3-Clause
Keywords: Jupyter,JupyterLab,JupyterLab3
Platform: Linux
Platform: Mac OS X
Platform: Windows
Classifier: License :: OSI Approved :: BSD License
Classifier: Programming Language :: Python
Classifier: Programming Language :: Python :: 3
Classifier: Programming Language :: Python :: 3.6
Classifier: Programming Language :: Python :: 3.7
Classifier: Programming Language :: Python :: 3.8
Classifier: Programming Language :: Python :: 3.9
Classifier: Programming Language :: Python :: 3.10
Classifier: Framework :: Jupyter
Classifier: Framework :: Jupyter :: JupyterLab
Classifier: Framework :: Jupyter :: JupyterLab :: 3
Classifier: Framework :: Jupyter :: JupyterLab :: Extensions
Classifier: Framework :: Jupyter :: JupyterLab :: Extensions :: Prebuilt
Requires-Python: >=3.6
Requires-Dist: jupyterlab (<4,>=3)
Requires-Dist: jupyter-server (<2,>=1.6)
Requires-Dist: globus-sdk (<4,>=3)
Requires-Dist: pydantic (>=1.9)
